mt5proxy
